requests_html.py
requests_html-0.9.0.dist-info/DESCRIPTION.rst
requests_html-0.9.0.dist-info/METADATA
requests_html-0.9.0.dist-info/RECORD
requests_html-0.9.0.dist-info/WHEEL
requests_html-0.9.0.dist-info/metadata.json
requests_html-0.9.0.dist-info/top_level.txt
