Metadata-Version: 1.2
Name: requests-html
Version: 0.9.0
Summary: HTML Parsing for Humans.
Home-page: https://github.com/kennethreitz/requests-html
Author: Kenneth Reitz
Author-email: me@kennethreitz.org
License: MIT
Platform: UNKNOWN
Classifier: License :: OSI Approved :: MIT License
Classifier: Programming Language :: Python
Classifier: Programming Language :: Python :: 3.6
Classifier: Programming Language :: Python :: Implementation :: CPython
Classifier: Programming Language :: Python :: Implementation :: PyPy
Requires-Python: >=3.6.0
